dry_pipe/__init__.py
dry_pipe/actions.py
dry_pipe/cli.py
dry_pipe/cli_screen.py
dry_pipe/internals.py
dry_pipe/janitors.py
dry_pipe/monitoring.py
dry_pipe/pipeline.py
dry_pipe/pipeline_state.py
dry_pipe/script_lib.py
dry_pipe/ssh_executer.py
dry_pipe/task.py
dry_pipe/task_state.py
dry_pipe/utils.py
dry_pipe-0.8.0.dist-info/METADATA
dry_pipe-0.8.0.dist-info/WHEEL
dry_pipe-0.8.0.dist-info/entry_points.txt
dry_pipe-0.8.0.dist-info/top_level.txt
dry_pipe-0.8.0.dist-info/RECORD
