Metadata-Version: 2.1
Name: dry-pipe
Version: 0.8.0
Summary: A Python DSL for bioinformatics pipelines
Home-page: https://github.com/calculs-ca/DryPipe
Author: Maxime Lévesque
Author-email: maxime.levesque@gmail.com
Project-URL: Bug Tracker, https://github.com/calculs-ca/DryPipe/issues
Project-URL: Documentation, https://drypipe.readthedocs.io
Classifier: Programming Language :: Python :: 3
Classifier: License :: OSI Approved :: Apache Software License
Classifier: Operating System :: OS Independent
Requires-Python: >=3.7.7
Requires-Dist: click (==8.1.3)
Requires-Dist: rich (==12.6.0)
Requires-Dist: requests (==2.27.1)
Requires-Dist: readchar (==4.0.3)
Requires-Dist: parallel-ssh (==2.12.0)
